{
  "username": "ziconkn_",
  "fullName": "",
  "biography": "",
  "externalUrl": null,
  "followers": 5947,
  "following": 2374,
  "posts": 3,
  "profilePic": "https://scontent-atl3-2.cdninstagram.com/v/t51.2885-19/559055822_18401389576185793_7731061224292974601_n.jpg?stp=dst-jpg_s320x320_tt6&efg=eyJ2ZW5jb2RlX3RhZyI6InByb2ZpbGVfcGljLmRqYW5nby42ODIuYzIifQ&_nc_ht=scontent-atl3-2.cdninstagram.com&_nc_cat=101&_nc_oc=Q6cZ2QGbPX3zpeKgGN8sIgRumkHN78rDwWlCGFg3B6rOoG_zf4mQ58plVqvvtDWZf5xVVHE&_nc_ohc=XGYE9T6LY8oQ7kNvwG2TXV_&_nc_gid=m33bX4YldwiQaGVpPmbzFg&edm=AOQ1c0wBAAAA&ccb=7-5&oh=00_AfmdHYT3ogRoBZiJXTc-8GceHDEbvcvaNpNFKx1mql2rQA&oe=693C3FE2&_nc_sid=8b3546",
  "private": false,
  "verified": false,
  "businessAccount": false,
  "professionalAccount": true,
  "category": "Cemetery",
  "joinedRecently": false,
  "highlightCount": 7,
  "hasChannel": false,
  "hasAREffects": false,
  "lastUpdate": "2025-12-08T07:27:31Z"
}
