{
  "username": "ziconkn_",
  "fullName": "",
  "biography": "",
  "externalUrl": null,
  "followers": 5954,
  "following": 2367,
  "posts": 3,
  "profilePic": "https://scontent-fra3-1.cdninstagram.com/v/t51.2885-19/559055822_18401389576185793_7731061224292974601_n.jpg?stp=dst-jpg_s320x320_tt6&efg=eyJ2ZW5jb2RlX3RhZyI6InByb2ZpbGVfcGljLmRqYW5nby42ODIuYzIifQ&_nc_ht=scontent-fra3-1.cdninstagram.com&_nc_cat=101&_nc_oc=Q6cZ2QGj3eZyIyy-p3jvvVJ-7XW5uZHjC13OLEsX_4hnppc1txsSMtqOCP8tTo2b37X9QiU&_nc_ohc=l5YtXCDkzZkQ7kNvwEX6f8s&_nc_gid=ufN08GLdp0-WpssnQVNq-w&edm=AOQ1c0wBAAAA&ccb=7-5&oh=00_Afka7VIYQBWg-6ietPbcTnljWxTh05ZAh6Y5rxfxi-rNYA&oe=6940A4E2&_nc_sid=8b3546",
  "private": false,
  "verified": false,
  "businessAccount": false,
  "professionalAccount": true,
  "category": "Cemetery",
  "joinedRecently": false,
  "highlightCount": 7,
  "hasChannel": false,
  "hasAREffects": false,
  "lastUpdate": "2025-12-11T15:29:36Z"
}
